xsar/__init__.py
xsar/base_dataset.py
xsar/base_meta.py
xsar/config.yml
xsar/ipython_backends.py
xsar/radarsat2_dataset.py
xsar/radarsat2_meta.py
xsar/raster_readers.py
xsar/sentinel1_dataset.py
xsar/sentinel1_meta.py
xsar/sentinel1_xml_mappings.py
xsar/utils.py
xsar/xarray_backends.py
xsar/xml_parser.py
xsar/xsar.py
xsar-1.0.0.data/scripts/compress_safe.py
xsar-1.0.0.dist-info/LICENSE
xsar-1.0.0.dist-info/METADATA
xsar-1.0.0.dist-info/WHEEL
xsar-1.0.0.dist-info/entry_points.txt
xsar-1.0.0.dist-info/top_level.txt
xsar-1.0.0.dist-info/RECORD
